git_archive_deep/__init__.py
git_archive_deep/__main__.py
git_archive_deep/py.typed
git_archive_deep-0.1.2.dist-info/entry_points.txt
git_archive_deep-0.1.2.dist-info/LICENSE
git_archive_deep-0.1.2.dist-info/WHEEL
git_archive_deep-0.1.2.dist-info/METADATA
git_archive_deep-0.1.2.dist-info/RECORD
