Metadata-Version: 2.1
Name: git-archive-deep
Version: 0.1.2
Summary: Git Archive Deep
Home-page: https://github.com/cd3/git-archive-deep
License: MIT
Author: CD Clark III
Author-email: clifton.clark@gmail.com
Requires-Python: >=3.7,<4.0
Classifier: Development Status :: 3 - Alpha
Classifier: License :: OSI Approved :: MIT License
Classifier: Programming Language :: Python :: 3
Classifier: Programming Language :: Python :: 3.10
Classifier: Programming Language :: Python :: 3.7
Classifier: Programming Language :: Python :: 3.8
Classifier: Programming Language :: Python :: 3.9
Requires-Dist: click (>=8.0.1)
Project-URL: Changelog, https://github.com/cd3/git-archive-deep/releases
Project-URL: Documentation, https://git-archive-deep.readthedocs.io
Project-URL: Repository, https://github.com/cd3/git-archive-deep
